<?xml version="1.0" encoding="utf-8"?>
<publishData>
  <publishProfile publishUrl="D:\Temp\DcmsMobile" deleteExistingFiles="True" ftpAnonymousLogin="False" ftpPassiveMode="True" msdeploySite="" msdeploySiteID="" msdeployRemoteSitePhysicalPath="" msdeployAllowUntrustedCertificate="False" msdeploySkipExtraFilesOnServer="True" msdeployMarkAsApp="False" profileName="DcmsMobile To China" publishMethod="FileSystem" replaceMatchingFiles="False" userName="" savePWD="False" userPWD="" SelectedForPublish="True">
    <file relUrl="App_Browsers/Ringscanner.browser" publishTime="01/10/2012 16:58:48" />
    <file relUrl="MvcDiagnostics.aspx" publishTime="01/10/2012 16:58:47" />
    <file relUrl="Content/themes/Default/images/ui-bg_gloss-wave_75_2191c0_500x100.png" publishTime="01/10/2012 16:58:48" />
    <file relUrl="Content/themes/Default/images/ui-bg_gloss-wave_50_6eac2c_500x100.png" publishTime="01/10/2012 16:58:48" />
    <file relUrl="Content/Images/MFLogo.jpg" publishTime="01/10/2012 16:58:48" />
    <file relUrl="Views/Logon/Profile.cshtml" publishTime="01/10/2012 16:58:48" />
    <file relUrl="Scripts/jquery-ui.min.js" publishTime="01/10/2012 16:58:47" />
    <file relUrl="Global.asax" publishTime="01/10/2012 16:58:47" />
    <file relUrl="Content/themes/Default/images/ui-icons_f7a50d_256x240.png" publishTime="01/10/2012 16:58:48" />
    <file relUrl="Scripts/jquery.validate.js" publishTime="01/10/2012 16:58:47" />
    <file relUrl="Views/Shared/_soundPartial.cshtml" publishTime="01/10/2012 16:58:48" />
    <file relUrl="Content/Sounds/warning.wav" publishTime="01/10/2012 16:58:48" />
    <file relUrl="Content/Images/a1.gif" publishTime="01/10/2012 16:58:48" />
    <file relUrl="Views/Diagnostic/Index.cshtml" publishTime="01/10/2012 16:58:47" />
    <file relUrl="bin/EclipseLibrary.Mvc.dll" publishTime="01/11/2012 17:15:28" />
    <file relUrl="Content/themes/Default/images/ui-icons_056b93_256x240.png" publishTime="01/10/2012 16:58:48" />
    <file relUrl="Scripts/jquery.min.js" publishTime="01/10/2012 16:58:47" />
    <file relUrl="Content/Sounds/Error.wav" publishTime="01/10/2012 16:58:48" />
    <file relUrl="Views/Diagnostic/Email.cshtml" publishTime="01/10/2012 16:58:47" />
    <file relUrl="Views/Shared/EditorTemplates/scan.cshtml" publishTime="01/10/2012 16:58:47" />
    <file relUrl="Views/Shared/Error.cshtml" publishTime="01/10/2012 16:58:47" />
    <file relUrl="Content/Sounds/BoxComplete.wav" publishTime="01/10/2012 16:58:48" />
    <file relUrl="Content/themes/Default/images/ui-bg_flat_75_aaaaaa_40x100.png" publishTime="01/10/2012 16:58:48" />
    <file relUrl="bin/EclipseLibrary.Oracle.dll" publishTime="01/11/2012 17:15:28" />
    <file relUrl="Views/_ViewStart.cshtml" publishTime="01/10/2012 16:58:47" />
    <file relUrl="Scripts/jquery.js" publishTime="01/10/2012 16:58:47" />
    <file relUrl="Scripts/scan.js" publishTime="01/10/2012 16:58:47" />
    <file relUrl="Views/Logon/ChangePassword.cshtml" publishTime="01/10/2012 16:58:48" />
    <file relUrl="bin/EclipseLibrary.Core.dll" publishTime="01/11/2012 17:15:28" />
    <file relUrl="Content/SiteMobile.css" publishTime="01/10/2012 16:58:48" />
    <file relUrl="Scripts/jquery.validate.unobtrusive.js" publishTime="01/10/2012 16:58:47" />
    <file relUrl="bin/AutoMapper.xml" publishTime="01/10/2012 16:58:43" />
    <file relUrl="Content/themes/Default/images/ui-icons_e0fdff_256x240.png" publishTime="01/10/2012 16:58:48" />
    <file relUrl="Content/themes/Default/images/ui-icons_d8e7f3_256x240.png" publishTime="01/10/2012 16:58:48" />
    <file relUrl="bin/AutoMapper.dll" publishTime="01/10/2012 16:58:43" />
    <file relUrl="Content/themes/Default/images/ui-bg_glass_55_f8da4e_1x400.png" publishTime="01/10/2012 16:58:48" />
    <file relUrl="Views/Logon/Index.Mobile.cshtml" publishTime="01/10/2012 16:58:48" />
    <file relUrl="Content/themes/Default/images/ui-bg_glass_45_0078ae_1x400.png" publishTime="01/10/2012 16:58:48" />
    <file relUrl="Scripts/jquery.validate.min.js" publishTime="01/10/2012 16:58:47" />
    <file relUrl="Content/themes/Default/images/ui-bg_glass_75_79c9ec_1x400.png" publishTime="01/10/2012 16:58:48" />
    <file relUrl="Content/themes/Default/images/ui-icons_fcd113_256x240.png" publishTime="01/10/2012 16:58:48" />
    <file relUrl="Views/Shared/_layoutMain.Mobile.cshtml" publishTime="01/10/2012 16:58:47" />
    <file relUrl="Views/Logon/Index.cshtml" publishTime="01/10/2012 16:58:48" />
    <file relUrl="Content/themes/Default/images/ui-bg_flat_55_999999_40x100.png" publishTime="01/10/2012 16:58:48" />
    <file relUrl="Views/Home/Launcher.Mobile.cshtml" publishTime="01/10/2012 16:58:48" />
    <file relUrl="Content/themes/Default/images/ui-bg_gloss-wave_45_e14f1c_500x100.png" publishTime="01/10/2012 16:58:48" />
    <file relUrl="Content/themes/Default/images/ui-bg_inset-hard_100_fcfdfd_1x100.png" publishTime="01/10/2012 16:58:48" />
    <file relUrl="Content/themes/Default/jquery-ui.min.css" publishTime="01/10/2012 16:58:48" />
    <file relUrl="Scripts/jquery-ui.js" publishTime="01/10/2012 16:58:47" />
    <file relUrl="Content/themes/Default/images/ui-icons_0078ae_256x240.png" publishTime="01/10/2012 16:58:48" />
    <file relUrl="Content/standardized.css" publishTime="01/10/2012 16:58:48" />
    <file relUrl="Views/Home/Launcher.cshtml" publishTime="01/10/2012 16:58:48" />
    <file relUrl="Web.config" publishTime="01/11/2012 17:15:35" />
    <file relUrl="Views/Shared/_layoutMain.cshtml" publishTime="01/11/2012 11:25:44" />
    <file relUrl="bin/DcmsMobile.dll" publishTime="01/11/2012 17:15:29" />
    <file relUrl="Content/Site.css" publishTime="01/10/2012 16:58:48" />
    <file relUrl="Doc/Tutorial.pptx" publishTime="01/11/2012 11:17:21" />
    <file relUrl="Content/Sounds/success.wav" publishTime="01/10/2012 16:58:48" />
    <file relUrl="Content/themes/Default/images/ui-icons_f5e175_256x240.png" publishTime="01/10/2012 16:58:48" />
    <file relUrl="Content/Images/calendar.gif" publishTime="01/10/2012 16:58:48" />
    <file relUrl="Scripts/jquery.validate.unobtrusive.min.js" publishTime="01/10/2012 16:58:47" />
    <file relUrl="Content/Images/ajax-loader.gif" publishTime="01/10/2012 16:58:48" />
    <file relUrl="Views/Web.config" publishTime="01/10/2012 16:58:47" />
    <file relUrl="Views/Shared/DisplayTemplates/ValueWithShortName.cshtml" publishTime="01/10/2012 16:58:47" />
  </publishProfile>
</publishData>